[
  {
    "orderId": "#CM9801",
    "user": "Natali Craig",
    "project": "Landing Page",
    "address": "Meadow Lane Oakland",
    "date": "Just now",
    "status": "In Progress"
  },
  {
    "orderId": "#CM9802",
    "user": "Kate Morrison",
    "project": "CRM Admin Pages",
    "address": "Larry Street San Francisco",
    "date": "A minute ago",
    "status": "Complete"
  },
  {
    "orderId": "#CM9803",
    "user": "Drew Cano",
    "project": "Client Project",
    "address": "Bagwell Avenue Ocala",
    "date": "5 minutes ago",
    "status": "Pending"
  },
  {
    "orderId": "#CM9804",
    "user": "Orlando Diggs",
    "project": "Admin Dashboard",
    "address": "Washburn Baton Rouge",
    "date": "1 hour ago",
    "status": "Approved"
  },
  {
    "orderId": "#CM9805",
    "user": "Andi Lane",
    "project": "App Landing Page",
    "address": "Nest Lane Olivette",
    "date": "2 hours ago",
    "status": "Rejected"
  },
  {
    "orderId": "#CM9806",
    "user": "Koray Okumus",
    "project": "Marketing Website",
    "address": "Sunset Blvd Los Angeles",
    "date": "Today",
    "status": "In Progress"
  },
  {
    "orderId": "#CM9807",
    "user": "Natali Craig",
    "project": "Portfolio Design",
    "address": "Park Avenue New York",
    "date": "Yesterday",
    "status": "Approved"
  },
  {
    "orderId": "#CM9808",
    "user": "Kate Morrison",
    "project": "E-commerce Store",
    "address": "Broadway Street Denver",
    "date": "Yesterday",
    "status": "Complete"
  },
  {
    "orderId": "#CM9809",
    "user": "Drew Cano",
    "project": "Client Dashboard",
    "address": "Lincoln Road Miami",
    "date": "2 days ago",
    "status": "Pending"
  },
  {
    "orderId": "#CM9810",
    "user": "Orlando Diggs",
    "project": "HR Management App",
    "address": "King Street Seattle",
    "date": "3 days ago",
    "status": "In Progress"
  },
  {
    "orderId": "#CM9811",
    "user": "Andi Lane",
    "project": "Blog Platform",
    "address": "Elm Street Dallas",
    "date": "Last week",
    "status": "Rejected"
  },
  {
    "orderId": "#CM9812",
    "user": "Koray Okumus",
    "project": "Analytics Dashboard",
    "address": "Highland Ave Boston",
    "date": "Last week",
    "status": "Approved"
  },
  {
    "orderId": "#CM9813",
    "user": "Natali Craig",
    "project": "Travel Website",
    "address": "Lakeview Drive Austin",
    "date": "Feb 10, 2023",
    "status": "Complete"
  },
  {
    "orderId": "#CM9814",
    "user": "Kate Morrison",
    "project": "Finance Tracker",
    "address": "Cedar Street Portland",
    "date": "Mar 5, 2023",
    "status": "Pending"
  },
  {
    "orderId": "#CM9815",
    "user": "Drew Cano",
    "project": "CRM Upgrade",
    "address": "Maple Road Chicago",
    "date": "Mar 8, 2023",
    "status": "Approved"
  },
  {
    "orderId": "#CM9816",
    "user": "Orlando Diggs",
    "project": "Learning Portal",
    "address": "Pine Street Nashville",
    "date": "Apr 1, 2023",
    "status": "Complete"
  },
  {
    "orderId": "#CM9817",
    "user": "Andi Lane",
    "project": "App Prototype",
    "address": "River Road Houston",
    "date": "Apr 9, 2023",
    "status": "In Progress"
  },
  {
    "orderId": "#CM9818",
    "user": "Koray Okumus",
    "project": "Game Website",
    "address": "Sunrise Ave Phoenix",
    "date": "May 1, 2023",
    "status": "Rejected"
  },
  {
    "orderId": "#CM9819",
    "user": "Natali Craig",
    "project": "Healthcare Portal",
    "address": "Greenway Blvd Tampa",
    "date": "May 12, 2023",
    "status": "Approved"
  },
  {
    "orderId": "#CM9820",
    "user": "Kate Morrison",
    "project": "Food Delivery App",
    "address": "Oak Lane Atlanta",
    "date": "Jun 1, 2023",
    "status": "Complete"
  },
  {
    "orderId": "#CM9821",
    "user": "Drew Cano",
    "project": "School Platform",
    "address": "Valley Street San Diego",
    "date": "Jun 15, 2023",
    "status": "Pending"
  },
  {
    "orderId": "#CM9822",
    "user": "Orlando Diggs",
    "project": "Ticket Booking",
    "address": "Grand Ave Detroit",
    "date": "Jun 28, 2023",
    "status": "In Progress"
  },
  {
    "orderId": "#CM9823",
    "user": "Andi Lane",
    "project": "Social Media Tool",
    "address": "Bridge Street Charlotte",
    "date": "Jul 7, 2023",
    "status": "Rejected"
  },
  {
    "orderId": "#CM9824",
    "user": "Koray Okumus",
    "project": "Streaming App",
    "address": "Harbor Drive Orlando",
    "date": "Jul 14, 2023",
    "status": "Approved"
  },
  {
    "orderId": "#CM9825",
    "user": "Natali Craig",
    "project": "Banking Portal",
    "address": "West Street Newark",
    "date": "Aug 1, 2023",
    "status": "Complete"
  },
  {
    "orderId": "#CM9826",
    "user": "Kate Morrison",
    "project": "Employee Hub",
    "address": "East Road Philadelphia",
    "date": "Aug 10, 2023",
    "status": "Approved"
  },
  {
    "orderId": "#CM9827",
    "user": "Drew Cano",
    "project": "Learning App",
    "address": "Birch Street Minneapolis",
    "date": "Aug 22, 2023",
    "status": "Rejected"
  },
  {
    "orderId": "#CM9828",
    "user": "Orlando Diggs",
    "project": "E-learning Portal",
    "address": "Canyon Road Kansas City",
    "date": "Sep 3, 2023",
    "status": "Pending"
  },
  {
    "orderId": "#CM9829",
    "user": "Andi Lane",
    "project": "Freelance Platform",
    "address": "Valley Road Salt Lake City",
    "date": "Sep 14, 2023",
    "status": "In Progress"
  },
  {
    "orderId": "#CM9830",
    "user": "Koray Okumus",
    "project": "Fitness Tracker",
    "address": "Summit Ave Las Vegas",
    "date": "Oct 2, 2023",
    "status": "Complete"
  },
  {
    "orderId": "#CM9831",
    "user": "Natali Craig",
    "project": "Donation Website",
    "address": "Willow Lane St. Louis",
    "date": "Oct 14, 2023",
    "status": "Approved"
  },
  {
    "orderId": "#CM9832",
    "user": "Kate Morrison",
    "project": "Portfolio Builder",
    "address": "Vine Street Memphis",
    "date": "Nov 1, 2023",
    "status": "Complete"
  },
  {
    "orderId": "#CM9833",
    "user": "Drew Cano",
    "project": "News Website",
    "address": "Cherry Avenue Columbus",
    "date": "Nov 10, 2023",
    "status": "Pending"
  },
  {
    "orderId": "#CM9834",
    "user": "Orlando Diggs",
    "project": "Chat Application",
    "address": "Peachtree Ave Atlanta",
    "date": "Nov 22, 2023",
    "status": "Rejected"
  },
  {
    "orderId": "#CM9835",
    "user": "Andi Lane",
    "project": "Ticketing Portal",
    "address": "Forest Lane Milwaukee",
    "date": "Dec 1, 2023",
    "status": "In Progress"
  },
  {
    "orderId": "#CM9836",
    "user": "Koray Okumus",
    "project": "Music Player",
    "address": "Market Street Baltimore",
    "date": "Dec 12, 2023",
    "status": "Approved"
  },
  {
    "orderId": "#CM9837",
    "user": "Natali Craig",
    "project": "Project Management Tool",
    "address": "Union Square San Jose",
    "date": "Jan 5, 2024",
    "status": "Rejected"
  },
  {
    "orderId": "#CM9838",
    "user": "Kate Morrison",
    "project": "Event Website",
    "address": "Central Park Ave Denver",
    "date": "Jan 15, 2024",
    "status": "Complete"
  },
  {
    "orderId": "#CM9839",
    "user": "Drew Cano",
    "project": "Logistics Dashboard",
    "address": "Broad Street Richmond",
    "date": "Jan 28, 2024",
    "status": "Approved"
  },
  {
    "orderId": "#CM9840",
    "user": "Orlando Diggs",
    "project": "Retail Website",
    "address": "Bridge Avenue Raleigh",
    "date": "Feb 2, 2024",
    "status": "In Progress"
  },
  {
    "orderId": "#CM9841",
    "user": "Andi Lane",
    "project": "Real Estate Portal",
    "address": "Sunset Road Tucson",
    "date": "Feb 20, 2024",
    "status": "Complete"
  },
  {
    "orderId": "#CM9842",
    "user": "Koray Okumus",
    "project": "Crowdfunding Platform",
    "address": "Lakeside Drive Boise",
    "date": "Mar 1, 2024",
    "status": "Pending"
  },
  {
    "orderId": "#CM9843",
    "user": "Natali Craig",
    "project": "Interior Design Site",
    "address": "Aspen Lane Spokane",
    "date": "Mar 18, 2024",
    "status": "Approved"
  },
  {
    "orderId": "#CM9844",
    "user": "Kate Morrison",
    "project": "Restaurant Website",
    "address": "Baker Street Louisville",
    "date": "Apr 2, 2024",
    "status": "In Progress"
  },
  {
    "orderId": "#CM9845",
    "user": "Drew Cano",
    "project": "Travel App",
    "address": "Canyon Blvd Denver",
    "date": "Apr 18, 2024",
    "status": "Rejected"
  },
  {
    "orderId": "#CM9846",
    "user": "Orlando Diggs",
    "project": "Sports Website",
    "address": "Liberty Road Pittsburgh",
    "date": "May 5, 2024",
    "status": "Approved"
  },
  {
    "orderId": "#CM9847",
    "user": "Andi Lane",
    "project": "Online Library",
    "address": "Heritage Street Cincinnati",
    "date": "May 15, 2024",
    "status": "Pending"
  },
  {
    "orderId": "#CM9848",
    "user": "Koray Okumus",
    "project": "Job Board",
    "address": "Innovation Blvd Austin",
    "date": "Jun 2, 2024",
    "status": "Complete"
  },
  {
    "orderId": "#CM9849",
    "user": "Natali Craig",
    "project": "Learning Hub",
    "address": "Willow Grove Sacramento",
    "date": "Jun 18, 2024",
    "status": "Rejected"
  },
  {
    "orderId": "#CM9850",
    "user": "Kate Morrison",
    "project": "Portfolio CMS",
    "address": "Ocean Drive Miami",
    "date": "Jul 1, 2024",
    "status": "Approved"
  }
]